YappatronBasicBrowser.py
yappatronbasicbrowser-0.1.1.dist-info/METADATA
yappatronbasicbrowser-0.1.1.dist-info/WHEEL
yappatronbasicbrowser-0.1.1.dist-info/top_level.txt
yappatronbasicbrowser-0.1.1.dist-info/RECORD
