Metadata-Version: 2.4
Name: YappatronBasicBrowser
Version: 0.1.1
Summary: A library for building a basic web browser with tabs in 2 lines of code.
Author-email: ZoeyDev <zoeydev@chickennet.work>
License: MIT
Requires-Python: >=3.11
Requires-Dist: PyQt6>=6.9.1
Requires-Dist: PyQt6-WebEngine>=6.9.0
